errortext/__init__.py
errortext-0.1.0.dist-info/LICENSE
errortext-0.1.0.dist-info/METADATA
errortext-0.1.0.dist-info/WHEEL
errortext-0.1.0.dist-info/top_level.txt
errortext-0.1.0.dist-info/RECORD
