Metadata-Version: 2.1
Name: errortext
Version: 0.1.0
Summary: Provide error messages for Python exceptions, even if the original message is empty
Home-page: https://github.com/roskakori/errortext
Author: Thomas Aglassinger
Author-email: roskakori@users.sourceforge.net
License: BSD
Project-URL: Changes, https://github.com/roskakori/errortext/blob/main/CHANGES.md
Project-URL: Issue Tracker, https://github.com/roskakori/errortext/issues
Keywords: error,error handling,error message,exception,exception handling
Platform: UNKNOWN
Classifier: Development Status :: 4 - Beta
Classifier: Intended Audience :: Developers
Classifier: License :: OSI Approved :: BSD License
Classifier: Natural Language :: English
Classifier: Operating System :: OS Independent
Classifier: Programming Language :: Python :: 3 :: Only
Classifier: Programming Language :: Python :: 3.6
Classifier: Programming Language :: Python :: 3.7
Classifier: Programming Language :: Python :: 3.8
Classifier: Programming Language :: Python :: 3.9
Classifier: Programming Language :: Python :: 3.10
Classifier: Topic :: Software Development
Requires-Python: >=3.6
